{
    "packMode": "packr",
    "platform": "macos_amd64",
    "dest": "D:\\Package\\EasyZK\\${appVersion}\\EasyZK_${appVersion}.app",
    "appIcon": "${projectPath}\\resource\\zoo.icns",
    "mainJar": "${projectPath}\\target\\easyzk-${appVersion}.jar",
    "jrePath": "D:\\Package\\EasyZK\\macos_amd64_jre23",
    "jdkPath": "$SYSTEM",
    "packr": {
        "verbose": true,
        "bundleIdentifier": "cn.oyzh.EasyZK",
        "mainClass": "org.springframework.boot.loader.JarLauncher",
        "classpath": []
    },
    "compress": {
        "type": "zip"
    },
    "jre": {
        "excludes": [
            "COPYRIGHT",
            "README.txt",
            "sound.properties",
            "ASSEMBLY_EXCEPTION",
            "ADDITIONAL_LICENSE_INFO",
            ".*.md",
            "jawt.*",
            "j2gss.*",
            "prefs.*",
            "jsound.*",
            "LICENSE.*",
            "javajpeg.*",
            "classlist.*",
            "jrunscript.*",
            "splashscreen.*"
        ]
    },
    "jar": {
        "removeEmpty": true,
        "excludes": [
            "pom.xml",
            "pom.properties",
            "AUTHORS",
            "README.md",
            "README.txt",
            "DEPENDENCIES",
            "aot.factories",
            "changelog.txt",
            "module-info.class",
            "latestchanges.html",
            "package-info.class",
            "ASSEMBLY_EXCEPTION",
            "reflectionconfig.json",
            "release-timestamp.txt",
            "ADDITIONAL_LICENSE_INFO",
            "reactor.blockhound.integration.BlockHoundIntegration",
            "classpath.idx",
            "LICENSE.*",
            ".*.md",
            ".*.pro",
            ".*.xsd",
            "NOTICE.*",
            ".*.tooling",
            ".*.schemas",
            ".*.handlers",
            "lombok-.*.jar",
            ".*.processors",
            ".*.kotlin_module",
            ".*.dll",
            ".*.so",
            "javafx-graphics.*-win.*.jar",
            "javafx-graphics*-linux.*.jar"
        ]
    }
}
